<annotation>
  <folder>VOC2007</folder>
  <filename>001360</filename>
  <source>
    <database>FDDB</database>
  </source>
  <size>
    <width>344</width>
    <height>450</height>
    <depth>3</depth>
  </size>
  <object>
    <name>face</name>
    <pose>Unspecified</pose>
    <truncated>0</truncated>
    <difficult>0</difficult>
    <bndbox>
      <xmin>80</xmin>
      <ymin>26</ymin>
      <xmax>247</xmax>
      <ymax>279</ymax>
    </bndbox>
  </object>
  <object>
    <name>face</name>
    <pose>Unspecified</pose>
    <truncated>0</truncated>
    <difficult>0</difficult>
    <bndbox>
      <xmin>4</xmin>
      <ymin>176</ymin>
      <xmax>77</xmax>
      <ymax>292</ymax>
    </bndbox>
  </object>
  <object>
    <name>face</name>
    <pose>Unspecified</pose>
    <truncated>0</truncated>
    <difficult>0</difficult>
    <bndbox>
      <xmin>209</xmin>
      <ymin>127</ymin>
      <xmax>326</xmax>
      <ymax>289</ymax>
    </bndbox>
  </object>
</annotation>
