<annotation>
  <folder>VOC2007</folder>
  <filename>002031</filename>
  <source>
    <database>FDDB</database>
  </source>
  <size>
    <width>450</width>
    <height>347</height>
    <depth>3</depth>
  </size>
  <object>
    <name>face</name>
    <pose>Unspecified</pose>
    <truncated>0</truncated>
    <difficult>0</difficult>
    <bndbox>
      <xmin>39</xmin>
      <ymin>14</ymin>
      <xmax>104</xmax>
      <ymax>120</ymax>
    </bndbox>
  </object>
  <object>
    <name>face</name>
    <pose>Unspecified</pose>
    <truncated>0</truncated>
    <difficult>0</difficult>
    <bndbox>
      <xmin>174</xmin>
      <ymin>35</ymin>
      <xmax>272</xmax>
      <ymax>191</ymax>
    </bndbox>
  </object>
  <object>
    <name>face</name>
    <pose>Unspecified</pose>
    <truncated>0</truncated>
    <difficult>0</difficult>
    <bndbox>
      <xmin>340</xmin>
      <ymin>73</ymin>
      <xmax>400</xmax>
      <ymax>164</ymax>
    </bndbox>
  </object>
</annotation>
